structurefunction.py
structurefunction-1.1.3.dist-info/LICENSE
structurefunction-1.1.3.dist-info/METADATA
structurefunction-1.1.3.dist-info/WHEEL
structurefunction-1.1.3.dist-info/top_level.txt
structurefunction-1.1.3.dist-info/RECORD
