Metadata-Version: 2.1
Name: structurefunction
Version: 1.1.3
Summary: Compute the second-order structure function
Home-page: https://github.com/AlecThomson/structurefunction
Author: Alec Thomson
Author-email: alec.thomson@csiro.au
License: MIT
Classifier: License :: OSI Approved :: MIT License
Classifier: Programming Language :: Python
Classifier: Programming Language :: Python :: 3
Classifier: Programming Language :: Python :: 3.6
Classifier: Programming Language :: Python :: Implementation :: CPython
Requires-Python: >=3.8.0
License-File: LICENSE
Requires-Dist: tqdm
Requires-Dist: numpy
Requires-Dist: astropy
Requires-Dist: matplotlib
Requires-Dist: bilby
Requires-Dist: ultranest
Requires-Dist: sigfig
Requires-Dist: nestle
Requires-Dist: xarray
Requires-Dist: numba
